collective.immediatecreate-2.0.1-py3.11-nspkg.pth
collective/immediatecreate/__init__.py
collective/immediatecreate/adding.py
collective/immediatecreate/behaviors.py
collective/immediatecreate/cleanup.py
collective/immediatecreate/configure.zcml
collective/immediatecreate/editing.py
collective/immediatecreate/events.py
collective/immediatecreate/indexer.py
collective/immediatecreate/interfaces.py
collective/immediatecreate/setuphandlers.py
collective/immediatecreate/testing.py
collective/immediatecreate/upgrades.py
collective/immediatecreate/upgrades.zcml
collective/immediatecreate/locales/collective.immediatecreate.pot
collective/immediatecreate/locales/update.sh
collective/immediatecreate/profiles/default/browserlayer.xml
collective/immediatecreate/profiles/default/catalog.xml
collective/immediatecreate/profiles/default/metadata.xml
collective/immediatecreate/profiles/uninstall/browserlayer.xml
collective/immediatecreate/profiles/uninstall/catalog.xml
collective/immediatecreate/tests/__init__.py
collective/immediatecreate/tests/test_adding.py
collective/immediatecreate/tests/test_robot.py
collective/immediatecreate/tests/test_setup.py
collective/immediatecreate/tests/robot/test_image.jpg
collective/immediatecreate/tests/robot/test_immediatecreate.robot
collective.immediatecreate-2.0.1.dist-info/LICENSE.GPL
collective.immediatecreate-2.0.1.dist-info/LICENSE.rst
collective.immediatecreate-2.0.1.dist-info/METADATA
collective.immediatecreate-2.0.1.dist-info/WHEEL
collective.immediatecreate-2.0.1.dist-info/entry_points.txt
collective.immediatecreate-2.0.1.dist-info/namespace_packages.txt
collective.immediatecreate-2.0.1.dist-info/top_level.txt
collective.immediatecreate-2.0.1.dist-info/RECORD
