Metadata-Version: 2.1
Name: collective.immediatecreate
Version: 2.0.1
Summary: Create dexterity items immediatly and skips add form.
Home-page: https://pypi.python.org/pypi/collective.immediatecreate
Author: Jens W. Klein
Author-email: jk@kleinundpartner.at
License: GPL version 2
Keywords: Python Plone
Classifier: Environment :: Web Environment
Classifier: Framework :: Plone
Classifier: Framework :: Plone :: Addon
Classifier: Framework :: Plone :: 6.0
Classifier: Programming Language :: Python
Classifier: Programming Language :: Python :: 3.9
Classifier: Programming Language :: Python :: 3.10
Classifier: Programming Language :: Python :: 3.11
Classifier: Operating System :: OS Independent
Classifier: License :: OSI Approved :: GNU General Public License v2 (GPLv2)
License-File: LICENSE.GPL
License-File: LICENSE.rst
Requires-Dist: Products.CMFPlone (>=6.0.0a2)
Requires-Dist: setuptools
Provides-Extra: test
Requires-Dist: plone.app.testing ; extra == 'test'
Requires-Dist: plone.testing (>=5.0.0) ; extra == 'test'
Requires-Dist: plone.app.robotframework[debug] ; extra == 'test'
